SkopeDataReader/AttrDict.py
SkopeDataReader/DataReader.py
SkopeDataReader/__init__.py
skopedatareader-1.3.1.dist-info/licenses/LICENSE
skopedatareader-1.3.1.dist-info/METADATA
skopedatareader-1.3.1.dist-info/WHEEL
skopedatareader-1.3.1.dist-info/top_level.txt
skopedatareader-1.3.1.dist-info/RECORD
