Metadata-Version: 2.4
Name: SkopeDataReader
Version: 1.3.1
Summary: Python reader to load data acquired with skope-fx
Author-email: Yolanda Duerst <yolanda.duerst@skope.ch>
License-File: LICENSE
Requires-Dist: numpy
Requires-Dist: scipy
Dynamic: license-file
